odoo10_addon_partner_sale_risk-10.0.1.0.2-nspkg.pth
odoo/addons/partner_sale_risk/README.rst
odoo/addons/partner_sale_risk/__init__.py
odoo/addons/partner_sale_risk/__manifest__.py
odoo/addons/partner_sale_risk/i18n/am.po
odoo/addons/partner_sale_risk/i18n/ar.po
odoo/addons/partner_sale_risk/i18n/bg.po
odoo/addons/partner_sale_risk/i18n/bs.po
odoo/addons/partner_sale_risk/i18n/ca.po
odoo/addons/partner_sale_risk/i18n/cs.po
odoo/addons/partner_sale_risk/i18n/da.po
odoo/addons/partner_sale_risk/i18n/de.po
odoo/addons/partner_sale_risk/i18n/el_GR.po
odoo/addons/partner_sale_risk/i18n/en_GB.po
odoo/addons/partner_sale_risk/i18n/es.po
odoo/addons/partner_sale_risk/i18n/es_CR.po
odoo/addons/partner_sale_risk/i18n/es_EC.po
odoo/addons/partner_sale_risk/i18n/es_ES.po
odoo/addons/partner_sale_risk/i18n/es_MX.po
odoo/addons/partner_sale_risk/i18n/es_VE.po
odoo/addons/partner_sale_risk/i18n/et.po
odoo/addons/partner_sale_risk/i18n/eu.po
odoo/addons/partner_sale_risk/i18n/fi.po
odoo/addons/partner_sale_risk/i18n/fr.po
odoo/addons/partner_sale_risk/i18n/fr_CA.po
odoo/addons/partner_sale_risk/i18n/fr_CH.po
odoo/addons/partner_sale_risk/i18n/gl.po
odoo/addons/partner_sale_risk/i18n/hr.po
odoo/addons/partner_sale_risk/i18n/hr_HR.po
odoo/addons/partner_sale_risk/i18n/hu.po
odoo/addons/partner_sale_risk/i18n/it.po
odoo/addons/partner_sale_risk/i18n/ja.po
odoo/addons/partner_sale_risk/i18n/lt.po
odoo/addons/partner_sale_risk/i18n/lv.po
odoo/addons/partner_sale_risk/i18n/mk.po
odoo/addons/partner_sale_risk/i18n/mn.po
odoo/addons/partner_sale_risk/i18n/nb.po
odoo/addons/partner_sale_risk/i18n/nb_NO.po
odoo/addons/partner_sale_risk/i18n/nl.po
odoo/addons/partner_sale_risk/i18n/nl_BE.po
odoo/addons/partner_sale_risk/i18n/partner_sale_risk.pot
odoo/addons/partner_sale_risk/i18n/pl.po
odoo/addons/partner_sale_risk/i18n/pt.po
odoo/addons/partner_sale_risk/i18n/pt_BR.po
odoo/addons/partner_sale_risk/i18n/pt_PT.po
odoo/addons/partner_sale_risk/i18n/ro.po
odoo10_addon_partner_sale_risk-10.0.1.0.2.dist-info/METADATA
odoo10_addon_partner_sale_risk-10.0.1.0.2.dist-info/WHEEL
odoo10_addon_partner_sale_risk-10.0.1.0.2.dist-info/namespace_packages.txt
odoo10_addon_partner_sale_risk-10.0.1.0.2.dist-info/top_level.txt
odoo10_addon_partner_sale_risk-10.0.1.0.2.dist-info/RECORD
