Metadata-Version: 2.1
Name: odoo10-addon-partner-sale-risk
Version: 10.0.1.0.2
Summary: Manage partner risk in sales orders
Home-page: https://www.tecnativa.com
Author: Tecnativa, Odoo Community Association (OCA)
Author-email: support@odoo-community.org
License: AGPL-3
Platform: UNKNOWN
Classifier: Programming Language :: Python
Classifier: Framework :: Odoo
Classifier: License :: OSI Approved :: GNU Affero General Public License v3
Requires-Python: ~=2.7
Requires-Dist: odoo10-addon-partner-financial-risk
Requires-Dist: odoo (<10.1dev,>=10.0)
